pytorch_adapt/__init__.py
pytorch_adapt/adapters/__init__.py
pytorch_adapt/adapters/adabn.py
pytorch_adapt/adapters/adda.py
pytorch_adapt/adapters/aligner.py
pytorch_adapt/adapters/base_adapter.py
pytorch_adapt/adapters/classifier.py
pytorch_adapt/adapters/dann.py
pytorch_adapt/adapters/gan.py
pytorch_adapt/adapters/mcd.py
pytorch_adapt/adapters/symnets.py
pytorch_adapt/adapters/utils.py
pytorch_adapt/containers/__init__.py
pytorch_adapt/containers/base_container.py
pytorch_adapt/containers/key_enforcer.py
pytorch_adapt/containers/lr_schedulers.py
pytorch_adapt/containers/misc.py
pytorch_adapt/containers/models.py
pytorch_adapt/containers/multiple_containers.py
pytorch_adapt/containers/optimizers.py
pytorch_adapt/datasets/__init__.py
pytorch_adapt/datasets/base_dataset.py
pytorch_adapt/datasets/clipart1k.py
pytorch_adapt/datasets/combined_source_and_target.py
pytorch_adapt/datasets/concat_dataset.py
pytorch_adapt/datasets/dataloader_creator.py
pytorch_adapt/datasets/domain_dataset.py
pytorch_adapt/datasets/domainnet.py
pytorch_adapt/datasets/getters.py
pytorch_adapt/datasets/mnistm.py
pytorch_adapt/datasets/office31.py
pytorch_adapt/datasets/officehome.py
pytorch_adapt/datasets/pseudo_labeled_dataset.py
pytorch_adapt/datasets/source_dataset.py
pytorch_adapt/datasets/target_dataset.py
pytorch_adapt/datasets/utils.py
pytorch_adapt/datasets/voc_multilabel.py
pytorch_adapt/frameworks/__init__.py
pytorch_adapt/frameworks/utils.py
pytorch_adapt/frameworks/ignite/__init__.py
pytorch_adapt/frameworks/ignite/checkpoint_utils.py
pytorch_adapt/frameworks/ignite/dictionary_accumulator.py
pytorch_adapt/frameworks/ignite/ignite.py
pytorch_adapt/frameworks/ignite/ignite_multilabel_classification.py
pytorch_adapt/frameworks/ignite/ignite_preds_as_features.py
pytorch_adapt/frameworks/ignite/ignite_val_hook_wrapper.py
pytorch_adapt/frameworks/ignite/utils.py
pytorch_adapt/frameworks/ignite/loggers/__init__.py
pytorch_adapt/frameworks/ignite/loggers/basic_loss_logger.py
pytorch_adapt-0.0.83.dist-info/LICENSE
pytorch_adapt-0.0.83.dist-info/METADATA
pytorch_adapt-0.0.83.dist-info/WHEEL
pytorch_adapt-0.0.83.dist-info/top_level.txt
pytorch_adapt-0.0.83.dist-info/RECORD
