Metadata-Version: 2.1
Name: pytorch-adapt
Version: 0.0.83
Summary: Domain adaptation made easy. Fully featured, modular, and customizable.
Home-page: https://github.com/KevinMusgrave/pytorch-adapt
Author: Kevin Musgrave
License: UNKNOWN
Platform: UNKNOWN
Classifier: Programming Language :: Python :: 3
Classifier: License :: OSI Approved :: MIT License
Classifier: Operating System :: OS Independent
Requires-Python: >=3.0
Requires-Dist: numpy
Requires-Dist: torch
Requires-Dist: torchvision
Requires-Dist: torchmetrics (==0.9.3)
Requires-Dist: pytorch-metric-learning (==1.6.3)
Provides-Extra: detection
Requires-Dist: albumentations (>=1.2.1) ; extra == 'detection'
Provides-Extra: dev
Requires-Dist: black ; extra == 'dev'
Requires-Dist: isort ; extra == 'dev'
Requires-Dist: nbqa ; extra == 'dev'
Requires-Dist: flake8 ; extra == 'dev'
Provides-Extra: docs
Requires-Dist: mkdocs-material ; extra == 'docs'
Requires-Dist: mkdocstrings[python] ; extra == 'docs'
Requires-Dist: griffe ; extra == 'docs'
Requires-Dist: mkdocs-gen-files ; extra == 'docs'
Requires-Dist: mkdocs-section-index ; extra == 'docs'
Requires-Dist: mkdocs-literate-nav ; extra == 'docs'
Provides-Extra: ignite
Requires-Dist: pytorch-ignite (==0.4.9) ; extra == 'ignite'
Provides-Extra: lightning
Requires-Dist: pytorch-lightning ; extra == 'lightning'
Provides-Extra: record-keeper
Requires-Dist: record-keeper (>=0.9.32) ; extra == 'record-keeper'
Requires-Dist: tensorboard ; extra == 'record-keeper'
Provides-Extra: timm
Requires-Dist: timm ; extra == 'timm'
